CHANGELOG.md
MANIFEST.in
README.md
requirements.txt
setup.py
test-requirements.txt
bin/backend_check
bin/graph_apply
bin/pipeline_check
bin/plan_check
bin/tf
bin/tf_apply
bin/tf_move
bin/visualize
terrawrap/__init__.py
terrawrap/exceptions.py
terrawrap/version.py
terrawrap.egg-info/PKG-INFO
terrawrap.egg-info/SOURCES.txt
terrawrap.egg-info/dependency_links.txt
terrawrap.egg-info/not-zip-safe
terrawrap.egg-info/requires.txt
terrawrap.egg-info/top_level.txt
terrawrap/models/__init__.py
terrawrap/models/config_mover.py
terrawrap/models/graph.py
terrawrap/models/graph_entry.py
terrawrap/models/pipeline.py
terrawrap/models/pipeline_entry.py
terrawrap/models/wrapper_config.py
terrawrap/utils/__init__.py
terrawrap/utils/cli.py
terrawrap/utils/collection_utils.py
terrawrap/utils/config.py
terrawrap/utils/dynamodb.py
terrawrap/utils/git_utils.py
terrawrap/utils/graph.py
terrawrap/utils/module.py
terrawrap/utils/path.py
terrawrap/utils/plugin_download.py
terrawrap/utils/terminal_colors.py
terrawrap/utils/tf_variables.py
terrawrap/utils/version.py