Metadata-Version: 2.4
Name: terrawrap
Version: 0.10.11
Summary: Set of Python-based CLI tools for working with Terraform configurations
Home-page: https://github.com/amplify-education/terrawrap
Author: Amplify Education
Author-email: github@amplify.com
License: MIT
Classifier: Development Status :: 4 - Beta
Classifier: Topic :: Software Development :: Libraries :: Python Modules
Classifier: Intended Audience :: Developers
Classifier: License :: OSI Approved :: MIT License
Classifier: Operating System :: OS Independent
Classifier: Programming Language :: Python
Classifier: Programming Language :: Python :: 3
Classifier: Programming Language :: Python :: 3.10
Classifier: Programming Language :: Python :: 3.11
Classifier: Programming Language :: Python :: 3.12
Classifier: Programming Language :: Python :: 3.13
Classifier: Programming Language :: Python :: 3.14
Requires-Python: >=3.10.0
Requires-Dist: amplify-aws-utils>=0.5.1
Requires-Dist: aws-requests-auth==0.4.3
Requires-Dist: docopt==0.6.2
Requires-Dist: filelock<4,>=3.0.12
Requires-Dist: gitpython>=2.1.10
Requires-Dist: PyYAML<7,>=6.0.1
Requires-Dist: ssm-cache<3,>=2.7
Requires-Dist: jsons<2.0.0,>=1.6.3
Requires-Dist: python-hcl2<4,>=3
Requires-Dist: packaging==23.1
Requires-Dist: diskcache<6,>=5.0.0
Requires-Dist: networkx>=2.4
Requires-Dist: python-dateutil<3,>=2.8.2
Requires-Dist: pytz<2023.1,>=2022.7.1
Requires-Dist: requests<3,>=2.32.2
Requires-Dist: boto3<2,>=1.34.116
Dynamic: author
Dynamic: author-email
Dynamic: classifier
Dynamic: description
Dynamic: description-content-type
Dynamic: home-page
Dynamic: keywords
Dynamic: license
Dynamic: requires-dist
Dynamic: requires-python
Dynamic: summary
